Metadata-Version: 2.1
Name: moneyfmt
Version: 1.0.3
Summary: Converte tipo Decimal para uma string formatda como dinheiro.
Home-page: http://gitlab.com/jonatanjrss/moneyfmt/
Author: Jonatan Rodrigues
Author-email: jonatanjrss@gmail.com
License: Copyright © 2001-2021 Python Software Foundation. All rights reserved.
Platform: any
Classifier: Development Status :: 5 - Production/Stable
Classifier: Framework :: Django
Classifier: Framework :: Flask
Classifier: Intended Audience :: Developers
Classifier: License :: OSI Approved :: MIT License
Classifier: Natural Language :: Portuguese
Classifier: Operating System :: OS Independent
Classifier: Programming Language :: Python
Classifier: Programming Language :: Python :: 3
Classifier: Topic :: Software Development :: Libraries
License-File: LICENSE
